[
    {
        "id": "a4d1c3f1-5b2a-4f7d-9d4b-8f0c2a6b7e21",
        "name": "Village Square",
        "description": "A lively crossroads ringed by cobbled stones and a moss-edged fountain. Roads splay to farms, trade stalls, and distant shrines.",
        "exits": [
            {
                "direction": "north",
                "to": "f7c9b2ad-1e34-4c6f-8d5a-2b7e9c4f1a53",
                "description": "The packed-earth lane leading toward the northern gate."
            },
            {
                "direction": "south",
                "to": "e1f2d3c4-b5a6-47e8-9f0a-1b2c3d4e5f6a",
                "description": "A rutted track toward the southern farms."
            },
            {
                "direction": "east",
                "to": "7a6d5c4b-3e2f-41a9-8b7c-9d0e1f2a3b4c",
                "description": "Canvas awnings and crates mark the merchant row."
            },
            {
                "direction": "west",
                "to": "2f1d7c9e-3b4a-45d8-9e6f-7a1c2b3d4e5f",
                "description": "Sharp clangs and smoke drift from the forge."
            },
            {
                "direction": "southeast",
                "to": "9c4b1f2e-5d6a-4e3b-8a7c-1d2f3e4a5b6c",
                "description": "Warm lantern light spills from the tavern arch."
            },
            {
                "direction": "southwest",
                "to": "4c3b2a1f-0e9d-48c7-b6a5-5d4e3f2a1b0c",
                "description": "Foot-worn path bending toward tilled soil."
            },
            {
                "direction": "northeast",
                "to": "8b7c6d5e-4f3a-42b1-9c8d-7e6f5a4b3c2d",
                "description": "A modest manor with a slate roof overlooks the square."
            },
            {
                "direction": "northwest",
                "to": "5e4d3c2b-1a0f-4b9e-8c7d-6a5b4c3d2e1f",
                "description": "Low stone walls and herb beds fringe a quiet yard."
            }
        ],
        "version": 1
    },
    {
        "id": "f7c9b2ad-1e34-4c6f-8d5a-2b7e9c4f1a53",
        "name": "North Road",
        "description": "The lane narrows between clustered cottages. Farther ahead a timber gate frames the road; the square lies back to the south.",
        "exits": [
            {"direction": "south", "to": "a4d1c3f1-5b2a-4f7d-9d4b-8f0c2a6b7e21", "description": "Back toward the bustling square."},
            {
                "direction": "north",
                "to": "3b0f5c88-6f27-4f0e-946d-3bdc4d7f9a11",
                "description": "A short stretch to the wooden palisade gate."
            }
        ],
        "version": 1
    },
    {
        "id": "3b0f5c88-6f27-4f0e-946d-3bdc4d7f9a11",
        "name": "North Gate",
        "description": "A simple palisade gate with watch planks overhead. Beyond, an overgrown path curls toward a crumbling shrine.",
        "exits": [
            {"direction": "south", "to": "f7c9b2ad-1e34-4c6f-8d5a-2b7e9c4f1a53", "description": "Back down the village road."},
            {
                "direction": "north",
                "to": "6e2d9a5b-8c3e-4b1a-b0f1-92d3c6e4f8d2",
                "description": "A tufted trail leading to mossy stonework."
            }
        ],
        "version": 1
    },
    {
        "id": "6e2d9a5b-8c3e-4b1a-b0f1-92d3c6e4f8d2",
        "name": "Old Hill Shrine",
        "description": "Weathered stones and lichen-crusted idols watch silently. Wildflowers reclaim the flagstones.",
        "exits": [
            {"direction": "south", "to": "3b0f5c88-6f27-4f0e-946d-3bdc4d7f9a11", "description": "Descend toward the village palisade."}
        ],
        "version": 1
    },
    {
        "id": "9c4b1f2e-5d6a-4e3b-8a7c-1d2f3e4a5b6c",
        "name": "Tavern Common Room",
        "description": "Low beams, roasted barley aroma, and a murmuring mix of travelers and locals. A hearth crackles at one end.",
        "exits": [
            {"direction": "northwest", "to": "a4d1c3f1-5b2a-4f7d-9d4b-8f0c2a6b7e21", "description": "Door swinging back to the square."},
            {"direction": "west", "to": "7a6d5c4b-3e2f-41a9-8b7c-9d0e1f2a3b4c", "description": "A side alley toward the merchant stalls."},
            {"direction": "south", "to": "e1f2d3c4-b5a6-47e8-9f0a-1b2c3d4e5f6a", "description": "Rear door opens onto the southern track."}
        ],
        "version": 1
    },
    {
        "id": "2f1d7c9e-3b4a-45d8-9e6f-7a1c2b3d4e5f",
        "name": "Blacksmith Forge",
        "description": "Sparks leap from the open-sided forge. Racks of half-finished tools and a barrel of quenched blades sit nearby.",
        "exits": [
            {"direction": "east", "to": "a4d1c3f1-5b2a-4f7d-9d4b-8f0c2a6b7e21", "description": "Step back into the open square."},
            {
                "direction": "south",
                "to": "4c3b2a1f-0e9d-48c7-b6a5-5d4e3f2a1b0c",
                "description": "A dirt path edging along vegetable plots."
            },
            {"direction": "north", "to": "5e4d3c2b-1a0f-4b9e-8c7d-6a5b4c3d2e1f", "description": "Stone steps up toward the walled garden."}
        ],
        "version": 1
    },
    {
        "id": "7a6d5c4b-3e2f-41a9-8b7c-9d0e1f2a3b4c",
        "name": "Trading Post Row",
        "description": "Makeshift stalls, stacked crates, and a chalkboard of prices. Merchants haggle over grain and iron nails.",
        "exits": [
            {"direction": "west", "to": "a4d1c3f1-5b2a-4f7d-9d4b-8f0c2a6b7e21", "description": "Back toward the fountain hub."},
            {
                "direction": "south",
                "to": "a9b8c7d6-e5f4-43a2-9b1c-0d2e3f4a5b6c",
                "description": "Wheel tracks leading to tilled eastern fields."
            },
            {"direction": "east", "to": "a9b8c7d6-e5f4-43a2-9b1c-0d2e3f4a5b6c", "description": "A narrow lane between small cottages."},
            {"direction": "southeast", "to": "9c4b1f2e-5d6a-4e3b-8a7c-1d2f3e4a5b6c", "description": "Covered walkway toward lantern light."}
        ],
        "version": 1
    },
    {
        "id": "5e4d3c2b-1a0f-4b9e-8c7d-6a5b4c3d2e1f",
        "name": "Herbalist Garden",
        "description": "Raised beds of pungent herbs within a low stone enclosure; glass jars and drying racks under a lean-to.",
        "exits": [
            {"direction": "southeast", "to": "a4d1c3f1-5b2a-4f7d-9d4b-8f0c2a6b7e21", "description": "Path sloping back to the square."},
            {"direction": "south", "to": "2f1d7c9e-3b4a-45d8-9e6f-7a1c2b3d4e5f", "description": "Steps down past stacked ore."},
            {"direction": "east", "to": "8b7c6d5e-4f3a-42b1-9c8d-7e6f5a4b3c2d", "description": "Gravel path to the manor door."}
        ],
        "version": 1
    },
    {
        "id": "8b7c6d5e-4f3a-42b1-9c8d-7e6f5a4b3c2d",
        "name": "Manor House",
        "description": "A modest two-story hall with carved lintels. Ledgers and a faded banner hint at civic duties.",
        "exits": [
            {
                "direction": "southwest",
                "to": "a4d1c3f1-5b2a-4f7d-9d4b-8f0c2a6b7e21",
                "description": "Stone steps descending to the square."
            },
            {"direction": "west", "to": "5e4d3c2b-1a0f-4b9e-8c7d-6a5b4c3d2e1f", "description": "Winding path among herb plots."}
        ],
        "version": 1
    },
    {
        "id": "4c3b2a1f-0e9d-48c7-b6a5-5d4e3f2a1b0c",
        "name": "West Farm Plot",
        "description": "Furrows of root vegetables and a small shed buzzing with grain moths. Chickens scatter near rough fencing.",
        "exits": [
            {"direction": "northeast", "to": "a4d1c3f1-5b2a-4f7d-9d4b-8f0c2a6b7e21", "description": "Trail leading back to the square."},
            {"direction": "east", "to": "e1f2d3c4-b5a6-47e8-9f0a-1b2c3d4e5f6a", "description": "Path merging with the southern track."},
            {"direction": "north", "to": "2f1d7c9e-3b4a-45d8-9e6f-7a1c2b3d4e5f", "description": "Path to the ringing hammer blows."}
        ],
        "version": 1
    },
    {
        "id": "e1f2d3c4-b5a6-47e8-9f0a-1b2c3d4e5f6a",
        "name": "South Road",
        "description": "A sun-warmed stretch bordered by low stone walls and carts laden with burlap sacks.",
        "exits": [
            {"direction": "north", "to": "a4d1c3f1-5b2a-4f7d-9d4b-8f0c2a6b7e21", "description": "Return to the central bustle."},
            {"direction": "south", "to": "d0c9b8a7-6e5f-41d2-8c3b-2a1f0e9d8c7b", "description": "Fields broaden toward distant hedgerows."},
            {"direction": "west", "to": "4c3b2a1f-0e9d-48c7-b6a5-5d4e3f2a1b0c", "description": "Wheel ruts veer toward western plots."},
            {
                "direction": "east",
                "to": "a9b8c7d6-e5f4-43a2-9b1c-0d2e3f4a5b6c",
                "description": "Dusty track bending past irrigation ditches."
            },
            {
                "direction": "northwest",
                "to": "4c3b2a1f-0e9d-48c7-b6a5-5d4e3f2a1b0c",
                "description": "Diagonal footpath skirting stacked hay."
            },
            {"direction": "northeast", "to": "7a6d5c4b-3e2f-41a9-8b7c-9d0e1f2a3b4c", "description": "Cut across to the merchant row."}
        ],
        "version": 1
    },
    {
        "id": "d0c9b8a7-6e5f-41d2-8c3b-2a1f0e9d8c7b",
        "name": "Southern Farmstead",
        "description": "Broad tilled earth, scarecrow shadows, and a creaking windlass over a shallow well.",
        "exits": [
            {"direction": "north", "to": "e1f2d3c4-b5a6-47e8-9f0a-1b2c3d4e5f6a", "description": "Track back toward the village heart."}
        ],
        "version": 1
    },
    {
        "id": "a9b8c7d6-e5f4-43a2-9b1c-0d2e3f4a5b6c",
        "name": "East Field Terraces",
        "description": "Tiered plots with young shoots, bordered by stacked stone and a lone elm tree.",
        "exits": [
            {"direction": "northwest", "to": "7a6d5c4b-3e2f-41a9-8b7c-9d0e1f2a3b4c", "description": "Cart path toward merchant stalls."},
            {"direction": "west", "to": "e1f2d3c4-b5a6-47e8-9f0a-1b2c3d4e5f6a", "description": "Follow the ruts to the main track."},
            {"direction": "north", "to": "7a6d5c4b-3e2f-41a9-8b7c-9d0e1f2a3b4c", "description": "Narrow lane between cottages."}
        ],
        "version": 1
    }
]
